mcp_recommender/__init__.py
mcp_recommender/__main__.py
mcp_recommender/__main__.py.backup
mcp_recommender/__main___asyncio_fixed.py
mcp_recommender/__main___backup.py
mcp_recommender/__main___fixed.py
mcp_recommender/__main___new.py
mcp_recommender/server.py
mcp_recommender/server_fixed.py
mcp_recommender/server_stdio.py
mcp_recommender/data/functional_keywords.json
mcp_recommender/data/mcp_database.json
mcp_recommender-0.1.0.dist-info/METADATA
mcp_recommender-0.1.0.dist-info/WHEEL
mcp_recommender-0.1.0.dist-info/entry_points.txt
mcp_recommender-0.1.0.dist-info/licenses/LICENSE
mcp_recommender-0.1.0.dist-info/RECORD
