Metadata-Version: 2.4
Name: mcp-recommender
Version: 0.1.0
Summary: A smart MCP server to recommend other MCPs based on your needs.
Project-URL: Homepage, https://github.com/your-username/mcp-recommender
Author-email: CodeBuddy <codebuddy@tencent.com>
License: MIT
License-File: LICENSE
Keywords: ai,mcp,model-context-protocol,recommendations,server
Classifier: Development Status :: 4 - Beta
Classifier: Intended Audience :: Developers
Classifier: License :: OSI Approved :: MIT License
Classifier: Programming Language :: Python :: 3
Classifier: Programming Language :: Python :: 3.10
Classifier: Programming Language :: Python :: 3.11
Classifier: Programming Language :: Python :: 3.12
Classifier: Programming Language :: Python :: 3.13
Classifier: Topic :: Internet :: WWW/HTTP :: HTTP Servers
Classifier: Topic :: Software Development :: Libraries :: Python Modules
Requires-Python: >=3.10
Requires-Dist: aiohttp>=3.8.0
Requires-Dist: build>=1.3.0
Requires-Dist: fastmcp>=0.4.0
Requires-Dist: requests>=2.31.0
Requires-Dist: twine>=6.1.0
Provides-Extra: dev
Requires-Dist: build>=1.3.0; extra == 'dev'
Requires-Dist: pytest>=7.0.0; extra == 'dev'
Requires-Dist: twine>=6.1.0; extra == 'dev'
